ezplugins/__init__.py
ezplugins/decorators.py
ezplugins/exceptions.py
ezplugins/manager.py
ezplugins/plugin.py
ezplugins/plugin_method.py
ezplugins/plugin_module.py
ezplugins-1.3.6.dist-info/LICENSE
ezplugins-1.3.6.dist-info/WHEEL
ezplugins-1.3.6.dist-info/METADATA
ezplugins-1.3.6.dist-info/RECORD
