Metadata-Version: 2.1
Name: ezplugins
Version: 1.3.6
Summary: EZPlugins is an easy to use plugin framework.
Keywords: framework,plugin,plugins
Author-email: Nigel Kukard <nkukard@LBSD.net>
Requires-Python: >=3.8
Classifier: Development Status :: 5 - Production/Stable
Classifier: Environment :: Plugins
Classifier: Intended Audience :: Developers
Classifier: License :: OSI Approved :: MIT License
Classifier: Programming Language :: Python :: 3 :: Only
Classifier: Topic :: Software Development
Project-URL: Documentation, https://software.pages.oscdev.io/ezplugins
Project-URL: Homepage, https://gitlab.oscdev.io/software/ezplugins
Project-URL: Issue Tracker, https://gitlab.oscdev.io/software/ezplugins/-/issues
Project-URL: Source Code, https://gitlab.oscdev.io/software/ezplugins
